nodanapy/__init__.py
nodanapy/wellNA.py
nodanapy/_properties/__init__.py
nodanapy/_properties/gasProperties.py
nodanapy/_properties/oilProperties.py
nodanapy/_properties/propertiesOGW.py
nodanapy/_properties/waterProperties.py
nodanapy/ipr/__init__.py
nodanapy/ipr/darcy.py
nodanapy/ipr/fetkovich.py
nodanapy/ipr/lit.py
nodanapy/ipr/vogel.py
nodanapy/vlp/__init__.py
nodanapy/vlp/beggsBrill.py
nodanapy/vlp/gray.py
nodanapy/vlp/hagedornBrown.py
nodanapy-1.0.2.dist-info/LICENSE
nodanapy-1.0.2.dist-info/METADATA
nodanapy-1.0.2.dist-info/WHEEL
nodanapy-1.0.2.dist-info/top_level.txt
nodanapy-1.0.2.dist-info/RECORD
