Metadata-Version: 2.1
Name: nodanapy
Version: 1.0.2
Summary: Package for determinig the Gas or Oil Wells' Nodal Analysis
Author: Ever J. Ramos I.
License:                    GNU LESSER GENERAL PUBLIC LICENSE
Project-URL: Homepage, https://github.com/EverJRamosI
Project-URL: Contact, https://www.linkedin.com/in/everjramosi/
Project-URL: Source Code, https://github.com/EverJRamosI/nodanapy
Project-URL: Bug Reports, https://github.com/EverJRamosI/nodanapy/issues
Keywords: petroleum,petroleum-engineering,oil-and-gas,nodal-analysis,reservoir
Classifier: Programming Language :: Python :: 3
Classifier: License :: OSI Approved :: GNU Lesser General Public License v3 (LGPLv3)
Classifier: Operating System :: OS Independent
Requires-Python: >=3.10
License-File: LICENSE
Requires-Dist: petpropy
Requires-Dist: numpy
Requires-Dist: pandas
Requires-Dist: scipy
